pystringbio/__init__.py
pystringbio/__main__.py
pystringbio/api/__init__.py
pystringbio/api/routes.py
pystringbio/api/schemas.py
pystringbio/client.py
pystringbio/fastapp.py
pystringbio/io/interactions.py
pystringbio/io/mapping.py
pystringbio/server.py
pystringbio/store/__init__.py
pystringbio/store/customError.py
pystringbio/store/interactions.py
pystringbio/store/mapper.py
pystringbio-0.1.1.dist-info/entry_points.txt
pystringbio-0.1.1.dist-info/WHEEL
pystringbio-0.1.1.dist-info/METADATA
pystringbio-0.1.1.dist-info/RECORD
