Metadata-Version: 2.1
Name: pystringbio
Version: 0.1.1
Summary: 
Author: glaunay
Author-email: pitooon@gmail.com
Requires-Python: >=3.7,<4.0
Classifier: Programming Language :: Python :: 3
Classifier: Programming Language :: Python :: 3.10
Classifier: Programming Language :: Python :: 3.7
Classifier: Programming Language :: Python :: 3.8
Classifier: Programming Language :: Python :: 3.9
Requires-Dist: docopt (>=0.6.2,<0.7.0)
Requires-Dist: fastapi (>=0.65.1,<0.66.0)
Requires-Dist: marshmallow (>=3.12.1,<4.0.0)
Requires-Dist: progressbar2 (>=3.53.1,<4.0.0)
Requires-Dist: prompt-toolkit (>=3.0.18,<4.0.0)
Requires-Dist: pydantic (>=1.8.2,<2.0.0)
Requires-Dist: pyrediscore (>=0.2.5,<0.3.0)
Requires-Dist: requests (>=2.25.1,<3.0.0)
Requires-Dist: uvicorn (>=0.13.4,<0.14.0)
